pandoc_latex_margin/__init__.py
pandoc_latex_margin/_main.py
pandoc_latex_margin-1.1.0.0.dist-info/METADATA
pandoc_latex_margin-1.1.0.0.dist-info/WHEEL
pandoc_latex_margin-1.1.0.0.dist-info/entry_points.txt
pandoc_latex_margin-1.1.0.0.dist-info/licenses/LICENSE
pandoc_latex_margin-1.1.0.0.dist-info/RECORD
